{
    "storage": [
        {
            "astId": 11198,
            "contract": "src/lib/LibGatewayActorStorage.sol:GatewayActorModifiers",
            "label": "s",
            "offset": 0,
            "slot": "0",
            "type": "t_struct(GatewayActorStorage)11184_storage"
        }
    ],
    "types": {
        "t_address": {
            "encoding": "inplace",
            "label": "address",
            "numberOfBytes": "20"
        },
        "t_array(t_address)dyn_storage": {
            "base": "t_address",
            "encoding": "dynamic_array",
            "label": "address[]",
            "numberOfBytes": "32"
        },
        "t_array(t_bytes32)dyn_storage": {
            "base": "t_bytes32",
            "encoding": "dynamic_array",
            "label": "bytes32[]",
            "numberOfBytes": "32"
        },
        "t_array(t_struct(IpcEnvelope)18040_storage)dyn_storage": {
            "base": "t_struct(IpcEnvelope)18040_storage",
            "encoding": "dynamic_array",
            "label": "struct IpcEnvelope[]",
            "numberOfBytes": "32"
        },
        "t_array(t_struct(Validator)18275_storage)dyn_storage": {
            "base": "t_struct(Validator)18275_storage",
            "encoding": "dynamic_array",
            "label": "struct Validator[]",
            "numberOfBytes": "32"
        },
        "t_bool": {
            "encoding": "inplace",
            "label": "bool",
            "numberOfBytes": "1"
        },
        "t_bytes32": {
            "encoding": "inplace",
            "label": "bytes32",
            "numberOfBytes": "32"
        },
        "t_bytes_storage": {
            "encoding": "bytes",
            "label": "bytes",
            "numberOfBytes": "32"
        },
        "t_enum(IpcMsgKind)18015": {
            "encoding": "inplace",
            "label": "enum IpcMsgKind",
            "numberOfBytes": "1"
        },
        "t_enum(PermissionMode)18229": {
            "encoding": "inplace",
            "label": "enum PermissionMode",
            "numberOfBytes": "1"
        },
        "t_enum(QuorumObjKind)18078": {
            "encoding": "inplace",
            "label": "enum QuorumObjKind",
            "numberOfBytes": "1"
        },
        "t_enum(StakingOperation)18160": {
            "encoding": "inplace",
            "label": "enum StakingOperation",
            "numberOfBytes": "1"
        },
        "t_mapping(t_address,t_bytes_storage)": {
            "encoding": "mapping",
            "key": "t_address",
            "label": "mapping(address => bytes)",
            "numberOfBytes": "32",
            "value": "t_bytes_storage"
        },
        "t_mapping(t_address,t_struct(ValidatorInfo)18225_storage)": {
            "encoding": "mapping",
            "key": "t_address",
            "label": "mapping(address => struct ValidatorInfo)",
            "numberOfBytes": "32",
            "value": "t_struct(ValidatorInfo)18225_storage"
        },
        "t_mapping(t_address,t_uint16)": {
            "encoding": "mapping",
            "key": "t_address",
            "label": "mapping(address => uint16)",
            "numberOfBytes": "32",
            "value": "t_uint16"
        },
        "t_mapping(t_bytes32,t_struct(IpcEnvelope)18040_storage)": {
            "encoding": "mapping",
            "key": "t_bytes32",
            "label": "mapping(bytes32 => struct IpcEnvelope)",
            "numberOfBytes": "32",
            "value": "t_struct(IpcEnvelope)18040_storage"
        },
        "t_mapping(t_bytes32,t_struct(Subnet)18155_storage)": {
            "encoding": "mapping",
            "key": "t_bytes32",
            "label": "mapping(bytes32 => struct Subnet)",
            "numberOfBytes": "32",
            "value": "t_struct(Subnet)18155_storage"
        },
        "t_mapping(t_bytes32,t_uint256)": {
            "encoding": "mapping",
            "key": "t_bytes32",
            "label": "mapping(bytes32 => uint256)",
            "numberOfBytes": "32",
            "value": "t_uint256"
        },
        "t_mapping(t_uint16,t_address)": {
            "encoding": "mapping",
            "key": "t_uint16",
            "label": "mapping(uint16 => address)",
            "numberOfBytes": "32",
            "value": "t_address"
        },
        "t_mapping(t_uint256,t_mapping(t_address,t_bytes_storage))": {
            "encoding": "mapping",
            "key": "t_uint256",
            "label": "mapping(uint256 => mapping(address => bytes))",
            "numberOfBytes": "32",
            "value": "t_mapping(t_address,t_bytes_storage)"
        },
        "t_mapping(t_uint256,t_struct(AddressSet)3814_storage)": {
            "encoding": "mapping",
            "key": "t_uint256",
            "label": "mapping(uint256 => struct EnumerableSet.AddressSet)",
            "numberOfBytes": "32",
            "value": "t_struct(AddressSet)3814_storage"
        },
        "t_mapping(t_uint256,t_struct(BottomUpCheckpoint)17975_storage)": {
            "encoding": "mapping",
            "key": "t_uint256",
            "label": "mapping(uint256 => struct BottomUpCheckpoint)",
            "numberOfBytes": "32",
            "value": "t_struct(BottomUpCheckpoint)17975_storage"
        },
        "t_mapping(t_uint256,t_struct(BottomUpMsgBatch)17988_storage)": {
            "encoding": "mapping",
            "key": "t_uint256",
            "label": "mapping(uint256 => struct BottomUpMsgBatch)",
            "numberOfBytes": "32",
            "value": "t_struct(BottomUpMsgBatch)17988_storage"
        },
        "t_mapping(t_uint256,t_struct(ParentFinality)17956_storage)": {
            "encoding": "mapping",
            "key": "t_uint256",
            "label": "mapping(uint256 => struct ParentFinality)",
            "numberOfBytes": "32",
            "value": "t_struct(ParentFinality)17956_storage"
        },
        "t_mapping(t_uint256,t_struct(QuorumInfo)18094_storage)": {
            "encoding": "mapping",
            "key": "t_uint256",
            "label": "mapping(uint256 => struct QuorumInfo)",
            "numberOfBytes": "32",
            "value": "t_struct(QuorumInfo)18094_storage"
        },
        "t_mapping(t_uint64,t_struct(StakingChange)18168_storage)": {
            "encoding": "mapping",
            "key": "t_uint64",
            "label": "mapping(uint64 => struct StakingChange)",
            "numberOfBytes": "32",
            "value": "t_struct(StakingChange)18168_storage"
        },
        "t_struct(AddressSet)3814_storage": {
            "encoding": "inplace",
            "label": "struct EnumerableSet.AddressSet",
            "members": [
                {
                    "astId": 3813,
                    "contract": "src/lib/LibGatewayActorStorage.sol:GatewayActorModifiers",
                    "label": "_inner",
                    "offset": 0,
                    "slot": "0",
                    "type": "t_struct(Set)3499_storage"
                }
            ],
            "numberOfBytes": "64"
        },
        "t_struct(BottomUpCheckpoint)17975_storage": {
            "encoding": "inplace",
            "label": "struct BottomUpCheckpoint",
            "members": [
                {
                    "astId": 17960,
                    "contract": "src/lib/LibGatewayActorStorage.sol:GatewayActorModifiers",
                    "label": "subnetID",
                    "offset": 0,
                    "slot": "0",
                    "type": "t_struct(SubnetID)18141_storage"
                },
                {
                    "astId": 17963,
                    "contract": "src/lib/LibGatewayActorStorage.sol:GatewayActorModifiers",
                    "label": "blockHeight",
                    "offset": 0,
                    "slot": "2",
                    "type": "t_uint256"
                },
                {
                    "astId": 17966,
                    "contract": "src/lib/LibGatewayActorStorage.sol:GatewayActorModifiers",
                    "label": "blockHash",
                    "offset": 0,
                    "slot": "3",
                    "type": "t_bytes32"
                },
                {
                    "astId": 17969,
                    "contract": "src/lib/LibGatewayActorStorage.sol:GatewayActorModifiers",
                    "label": "nextConfigurationNumber",
                    "offset": 0,
                    "slot": "4",
                    "type": "t_uint64"
                },
                {
                    "astId": 17974,
                    "contract": "src/lib/LibGatewayActorStorage.sol:GatewayActorModifiers",
                    "label": "msgs",
                    "offset": 0,
                    "slot": "5",
                    "type": "t_array(t_struct(IpcEnvelope)18040_storage)dyn_storage"
                }
            ],
            "numberOfBytes": "192"
        },
        "t_struct(BottomUpMsgBatch)17988_storage": {
            "encoding": "inplace",
            "label": "struct BottomUpMsgBatch",
            "members": [
                {
                    "astId": 17979,
                    "contract": "src/lib/LibGatewayActorStorage.sol:GatewayActorModifiers",
                    "label": "subnetID",
                    "offset": 0,
                    "slot": "0",
                    "type": "t_struct(SubnetID)18141_storage"
                },
                {
                    "astId": 17982,
                    "contract": "src/lib/LibGatewayActorStorage.sol:GatewayActorModifiers",
                    "label": "blockHeight",
                    "offset": 0,
                    "slot": "2",
                    "type": "t_uint256"
                },
                {
                    "astId": 17987,
                    "contract": "src/lib/LibGatewayActorStorage.sol:GatewayActorModifiers",
                    "label": "msgs",
                    "offset": 0,
                    "slot": "3",
                    "type": "t_array(t_struct(IpcEnvelope)18040_storage)dyn_storage"
                }
            ],
            "numberOfBytes": "128"
        },
        "t_struct(FvmAddress)18064_storage": {
            "encoding": "inplace",
            "label": "struct FvmAddress",
            "members": [
                {
                    "astId": 18061,
                    "contract": "src/lib/LibGatewayActorStorage.sol:GatewayActorModifiers",
                    "label": "addrType",
                    "offset": 0,
                    "slot": "0",
                    "type": "t_uint8"
                },
                {
                    "astId": 18063,
                    "contract": "src/lib/LibGatewayActorStorage.sol:GatewayActorModifiers",
                    "label": "payload",
                    "offset": 0,
                    "slot": "1",
                    "type": "t_bytes_storage"
                }
            ],
            "numberOfBytes": "64"
        },
        "t_struct(GatewayActorStorage)11184_storage": {
            "encoding": "inplace",
            "label": "struct GatewayActorStorage",
            "members": [
                {
                    "astId": 11096,
                    "contract": "src/lib/LibGatewayActorStorage.sol:GatewayActorModifiers",
                    "label": "subnets",
                    "offset": 0,
                    "slot": "0",
                    "type": "t_mapping(t_bytes32,t_struct(Subnet)18155_storage)"
                },
                {
                    "astId": 11102,
                    "contract": "src/lib/LibGatewayActorStorage.sol:GatewayActorModifiers",
                    "label": "finalitiesMap",
                    "offset": 0,
                    "slot": "1",
                    "type": "t_mapping(t_uint256,t_struct(ParentFinality)17956_storage)"
                },
                {
                    "astId": 11105,
                    "contract": "src/lib/LibGatewayActorStorage.sol:GatewayActorModifiers",
                    "label": "latestParentHeight",
                    "offset": 0,
                    "slot": "2",
                    "type": "t_uint256"
                },
                {
                    "astId": 11111,
                    "contract": "src/lib/LibGatewayActorStorage.sol:GatewayActorModifiers",
                    "label": "postbox",
                    "offset": 0,
                    "slot": "3",
                    "type": "t_mapping(t_bytes32,t_struct(IpcEnvelope)18040_storage)"
                },
                {
                    "astId": 11115,
                    "contract": "src/lib/LibGatewayActorStorage.sol:GatewayActorModifiers",
                    "label": "currentMembership",
                    "offset": 0,
                    "slot": "4",
                    "type": "t_struct(Membership)18282_storage"
                },
                {
                    "astId": 11119,
                    "contract": "src/lib/LibGatewayActorStorage.sol:GatewayActorModifiers",
                    "label": "lastMembership",
                    "offset": 0,
                    "slot": "6",
                    "type": "t_struct(Membership)18282_storage"
                },
                {
                    "astId": 11125,
                    "contract": "src/lib/LibGatewayActorStorage.sol:GatewayActorModifiers",
                    "label": "bottomUpCheckpoints",
                    "offset": 0,
                    "slot": "8",
                    "type": "t_mapping(t_uint256,t_struct(BottomUpCheckpoint)17975_storage)"
                },
                {
                    "astId": 11131,
                    "contract": "src/lib/LibGatewayActorStorage.sol:GatewayActorModifiers",
                    "label": "bottomUpMsgBatches",
                    "offset": 0,
                    "slot": "9",
                    "type": "t_mapping(t_uint256,t_struct(BottomUpMsgBatch)17988_storage)"
                },
                {
                    "astId": 11135,
                    "contract": "src/lib/LibGatewayActorStorage.sol:GatewayActorModifiers",
                    "label": "checkpointQuorumMap",
                    "offset": 0,
                    "slot": "10",
                    "type": "t_struct(QuorumMap)18125_storage"
                },
                {
                    "astId": 11139,
                    "contract": "src/lib/LibGatewayActorStorage.sol:GatewayActorModifiers",
                    "label": "subnetKeys",
                    "offset": 0,
                    "slot": "17",
                    "type": "t_array(t_bytes32)dyn_storage"
                },
                {
                    "astId": 11143,
                    "contract": "src/lib/LibGatewayActorStorage.sol:GatewayActorModifiers",
                    "label": "networkName",
                    "offset": 0,
                    "slot": "18",
                    "type": "t_struct(SubnetID)18141_storage"
                },
                {
                    "astId": 11146,
                    "contract": "src/lib/LibGatewayActorStorage.sol:GatewayActorModifiers",
                    "label": "minCrossMsgFee",
                    "offset": 0,
                    "slot": "20",
                    "type": "t_uint256"
                },
                {
                    "astId": 11149,
                    "contract": "src/lib/LibGatewayActorStorage.sol:GatewayActorModifiers",
                    "label": "majorityPercentage",
                    "offset": 0,
                    "slot": "21",
                    "type": "t_uint8"
                },
                {
                    "astId": 11152,
                    "contract": "src/lib/LibGatewayActorStorage.sol:GatewayActorModifiers",
                    "label": "bottomUpNonce",
                    "offset": 1,
                    "slot": "21",
                    "type": "t_uint64"
                },
                {
                    "astId": 11155,
                    "contract": "src/lib/LibGatewayActorStorage.sol:GatewayActorModifiers",
                    "label": "appliedTopDownNonce",
                    "offset": 9,
                    "slot": "21",
                    "type": "t_uint64"
                },
                {
                    "astId": 11158,
                    "contract": "src/lib/LibGatewayActorStorage.sol:GatewayActorModifiers",
                    "label": "totalSubnets",
                    "offset": 17,
                    "slot": "21",
                    "type": "t_uint64"
                },
                {
                    "astId": 11161,
                    "contract": "src/lib/LibGatewayActorStorage.sol:GatewayActorModifiers",
                    "label": "bottomUpCheckPeriod",
                    "offset": 0,
                    "slot": "22",
                    "type": "t_uint256"
                },
                {
                    "astId": 11164,
                    "contract": "src/lib/LibGatewayActorStorage.sol:GatewayActorModifiers",
                    "label": "maxMsgsPerBottomUpBatch",
                    "offset": 0,
                    "slot": "23",
                    "type": "t_uint64"
                },
                {
                    "astId": 11168,
                    "contract": "src/lib/LibGatewayActorStorage.sol:GatewayActorModifiers",
                    "label": "validatorsTracker",
                    "offset": 0,
                    "slot": "24",
                    "type": "t_struct(ParentValidatorsTracker)18261_storage"
                },
                {
                    "astId": 11171,
                    "contract": "src/lib/LibGatewayActorStorage.sol:GatewayActorModifiers",
                    "label": "maxTreeDepth",
                    "offset": 0,
                    "slot": "35",
                    "type": "t_uint8"
                },
                {
                    "astId": 11174,
                    "contract": "src/lib/LibGatewayActorStorage.sol:GatewayActorModifiers",
                    "label": "generalPurposeCrossMsg",
                    "offset": 1,
                    "slot": "35",
                    "type": "t_bool"
                },
                {
                    "astId": 11177,
                    "contract": "src/lib/LibGatewayActorStorage.sol:GatewayActorModifiers",
                    "label": "multiLevelCrossMsg",
                    "offset": 2,
                    "slot": "35",
                    "type": "t_bool"
                },
                {
                    "astId": 11180,
                    "contract": "src/lib/LibGatewayActorStorage.sol:GatewayActorModifiers",
                    "label": "checkpointRelayerRewards",
                    "offset": 3,
                    "slot": "35",
                    "type": "t_bool"
                },
                {
                    "astId": 11183,
                    "contract": "src/lib/LibGatewayActorStorage.sol:GatewayActorModifiers",
                    "label": "crossMsgRelayerRewards",
                    "offset": 4,
                    "slot": "35",
                    "type": "t_bool"
                }
            ],
            "numberOfBytes": "1152"
        },
        "t_struct(IPCAddress)18268_storage": {
            "encoding": "inplace",
            "label": "struct IPCAddress",
            "members": [
                {
                    "astId": 18264,
                    "contract": "src/lib/LibGatewayActorStorage.sol:GatewayActorModifiers",
                    "label": "subnetId",
                    "offset": 0,
                    "slot": "0",
                    "type": "t_struct(SubnetID)18141_storage"
                },
                {
                    "astId": 18267,
                    "contract": "src/lib/LibGatewayActorStorage.sol:GatewayActorModifiers",
                    "label": "rawAddress",
                    "offset": 0,
                    "slot": "2",
                    "type": "t_struct(FvmAddress)18064_storage"
                }
            ],
            "numberOfBytes": "128"
        },
        "t_struct(IpcEnvelope)18040_storage": {
            "encoding": "inplace",
            "label": "struct IpcEnvelope",
            "members": [
                {
                    "astId": 18019,
                    "contract": "src/lib/LibGatewayActorStorage.sol:GatewayActorModifiers",
                    "label": "kind",
                    "offset": 0,
                    "slot": "0",
                    "type": "t_enum(IpcMsgKind)18015"
                },
                {
                    "astId": 18023,
                    "contract": "src/lib/LibGatewayActorStorage.sol:GatewayActorModifiers",
                    "label": "to",
                    "offset": 0,
                    "slot": "1",
                    "type": "t_struct(IPCAddress)18268_storage"
                },
                {
                    "astId": 18027,
                    "contract": "src/lib/LibGatewayActorStorage.sol:GatewayActorModifiers",
                    "label": "from",
                    "offset": 0,
                    "slot": "5",
                    "type": "t_struct(IPCAddress)18268_storage"
                },
                {
                    "astId": 18030,
                    "contract": "src/lib/LibGatewayActorStorage.sol:GatewayActorModifiers",
                    "label": "value",
                    "offset": 0,
                    "slot": "9",
                    "type": "t_uint256"
                },
                {
                    "astId": 18033,
                    "contract": "src/lib/LibGatewayActorStorage.sol:GatewayActorModifiers",
                    "label": "message",
                    "offset": 0,
                    "slot": "10",
                    "type": "t_bytes_storage"
                },
                {
                    "astId": 18036,
                    "contract": "src/lib/LibGatewayActorStorage.sol:GatewayActorModifiers",
                    "label": "nonce",
                    "offset": 0,
                    "slot": "11",
                    "type": "t_uint64"
                },
                {
                    "astId": 18039,
                    "contract": "src/lib/LibGatewayActorStorage.sol:GatewayActorModifiers",
                    "label": "fee",
                    "offset": 0,
                    "slot": "12",
                    "type": "t_uint256"
                }
            ],
            "numberOfBytes": "416"
        },
        "t_struct(MaxPQ)16449_storage": {
            "encoding": "inplace",
            "label": "struct MaxPQ",
            "members": [
                {
                    "astId": 16448,
                    "contract": "src/lib/LibGatewayActorStorage.sol:GatewayActorModifiers",
                    "label": "inner",
                    "offset": 0,
                    "slot": "0",
                    "type": "t_struct(PQ)17696_storage"
                }
            ],
            "numberOfBytes": "96"
        },
        "t_struct(Membership)18282_storage": {
            "encoding": "inplace",
            "label": "struct Membership",
            "members": [
                {
                    "astId": 18279,
                    "contract": "src/lib/LibGatewayActorStorage.sol:GatewayActorModifiers",
                    "label": "validators",
                    "offset": 0,
                    "slot": "0",
                    "type": "t_array(t_struct(Validator)18275_storage)dyn_storage"
                },
                {
                    "astId": 18281,
                    "contract": "src/lib/LibGatewayActorStorage.sol:GatewayActorModifiers",
                    "label": "configurationNumber",
                    "offset": 0,
                    "slot": "1",
                    "type": "t_uint64"
                }
            ],
            "numberOfBytes": "64"
        },
        "t_struct(MinPQ)17067_storage": {
            "encoding": "inplace",
            "label": "struct MinPQ",
            "members": [
                {
                    "astId": 17066,
                    "contract": "src/lib/LibGatewayActorStorage.sol:GatewayActorModifiers",
                    "label": "inner",
                    "offset": 0,
                    "slot": "0",
                    "type": "t_struct(PQ)17696_storage"
                }
            ],
            "numberOfBytes": "96"
        },
        "t_struct(PQ)17696_storage": {
            "encoding": "inplace",
            "label": "struct PQ",
            "members": [
                {
                    "astId": 17685,
                    "contract": "src/lib/LibGatewayActorStorage.sol:GatewayActorModifiers",
                    "label": "size",
                    "offset": 0,
                    "slot": "0",
                    "type": "t_uint16"
                },
                {
                    "astId": 17690,
                    "contract": "src/lib/LibGatewayActorStorage.sol:GatewayActorModifiers",
                    "label": "addressToPos",
                    "offset": 0,
                    "slot": "1",
                    "type": "t_mapping(t_address,t_uint16)"
                },
                {
                    "astId": 17695,
                    "contract": "src/lib/LibGatewayActorStorage.sol:GatewayActorModifiers",
                    "label": "posToAddress",
                    "offset": 0,
                    "slot": "2",
                    "type": "t_mapping(t_uint16,t_address)"
                }
            ],
            "numberOfBytes": "96"
        },
        "t_struct(ParentFinality)17956_storage": {
            "encoding": "inplace",
            "label": "struct ParentFinality",
            "members": [
                {
                    "astId": 17953,
                    "contract": "src/lib/LibGatewayActorStorage.sol:GatewayActorModifiers",
                    "label": "height",
                    "offset": 0,
                    "slot": "0",
                    "type": "t_uint256"
                },
                {
                    "astId": 17955,
                    "contract": "src/lib/LibGatewayActorStorage.sol:GatewayActorModifiers",
                    "label": "blockHash",
                    "offset": 0,
                    "slot": "1",
                    "type": "t_bytes32"
                }
            ],
            "numberOfBytes": "64"
        },
        "t_struct(ParentValidatorsTracker)18261_storage": {
            "encoding": "inplace",
            "label": "struct ParentValidatorsTracker",
            "members": [
                {
                    "astId": 18257,
                    "contract": "src/lib/LibGatewayActorStorage.sol:GatewayActorModifiers",
                    "label": "validators",
                    "offset": 0,
                    "slot": "0",
                    "type": "t_struct(ValidatorSet)18254_storage"
                },
                {
                    "astId": 18260,
                    "contract": "src/lib/LibGatewayActorStorage.sol:GatewayActorModifiers",
                    "label": "changes",
                    "offset": 0,
                    "slot": "9",
                    "type": "t_struct(StakingChangeLog)18187_storage"
                }
            ],
            "numberOfBytes": "352"
        },
        "t_struct(QuorumInfo)18094_storage": {
            "encoding": "inplace",
            "label": "struct QuorumInfo",
            "members": [
                {
                    "astId": 18081,
                    "contract": "src/lib/LibGatewayActorStorage.sol:GatewayActorModifiers",
                    "label": "hash",
                    "offset": 0,
                    "slot": "0",
                    "type": "t_bytes32"
                },
                {
                    "astId": 18084,
                    "contract": "src/lib/LibGatewayActorStorage.sol:GatewayActorModifiers",
                    "label": "rootHash",
                    "offset": 0,
                    "slot": "1",
                    "type": "t_bytes32"
                },
                {
                    "astId": 18087,
                    "contract": "src/lib/LibGatewayActorStorage.sol:GatewayActorModifiers",
                    "label": "threshold",
                    "offset": 0,
                    "slot": "2",
                    "type": "t_uint256"
                },
                {
                    "astId": 18090,
                    "contract": "src/lib/LibGatewayActorStorage.sol:GatewayActorModifiers",
                    "label": "currentWeight",
                    "offset": 0,
                    "slot": "3",
                    "type": "t_uint256"
                },
                {
                    "astId": 18093,
                    "contract": "src/lib/LibGatewayActorStorage.sol:GatewayActorModifiers",
                    "label": "reached",
                    "offset": 0,
                    "slot": "4",
                    "type": "t_bool"
                }
            ],
            "numberOfBytes": "160"
        },
        "t_struct(QuorumMap)18125_storage": {
            "encoding": "inplace",
            "label": "struct QuorumMap",
            "members": [
                {
                    "astId": 18098,
                    "contract": "src/lib/LibGatewayActorStorage.sol:GatewayActorModifiers",
                    "label": "quorumObjKind",
                    "offset": 0,
                    "slot": "0",
                    "type": "t_enum(QuorumObjKind)18078"
                },
                {
                    "astId": 18101,
                    "contract": "src/lib/LibGatewayActorStorage.sol:GatewayActorModifiers",
                    "label": "retentionHeight",
                    "offset": 0,
                    "slot": "1",
                    "type": "t_uint256"
                },
                {
                    "astId": 18107,
                    "contract": "src/lib/LibGatewayActorStorage.sol:GatewayActorModifiers",
                    "label": "quorumInfo",
                    "offset": 0,
                    "slot": "2",
                    "type": "t_mapping(t_uint256,t_struct(QuorumInfo)18094_storage)"
                },
                {
                    "astId": 18111,
                    "contract": "src/lib/LibGatewayActorStorage.sol:GatewayActorModifiers",
                    "label": "incompleteQuorums",
                    "offset": 0,
                    "slot": "3",
                    "type": "t_struct(UintSet)3971_storage"
                },
                {
                    "astId": 18117,
                    "contract": "src/lib/LibGatewayActorStorage.sol:GatewayActorModifiers",
                    "label": "quorumSignatureSenders",
                    "offset": 0,
                    "slot": "5",
                    "type": "t_mapping(t_uint256,t_struct(AddressSet)3814_storage)"
                },
                {
                    "astId": 18124,
                    "contract": "src/lib/LibGatewayActorStorage.sol:GatewayActorModifiers",
                    "label": "quorumSignatures",
                    "offset": 0,
                    "slot": "6",
                    "type": "t_mapping(t_uint256,t_mapping(t_address,t_bytes_storage))"
                }
            ],
            "numberOfBytes": "224"
        },
        "t_struct(Set)3499_storage": {
            "encoding": "inplace",
            "label": "struct EnumerableSet.Set",
            "members": [
                {
                    "astId": 3494,
                    "contract": "src/lib/LibGatewayActorStorage.sol:GatewayActorModifiers",
                    "label": "_values",
                    "offset": 0,
                    "slot": "0",
                    "type": "t_array(t_bytes32)dyn_storage"
                },
                {
                    "astId": 3498,
                    "contract": "src/lib/LibGatewayActorStorage.sol:GatewayActorModifiers",
                    "label": "_indexes",
                    "offset": 0,
                    "slot": "1",
                    "type": "t_mapping(t_bytes32,t_uint256)"
                }
            ],
            "numberOfBytes": "64"
        },
        "t_struct(StakingChange)18168_storage": {
            "encoding": "inplace",
            "label": "struct StakingChange",
            "members": [
                {
                    "astId": 18163,
                    "contract": "src/lib/LibGatewayActorStorage.sol:GatewayActorModifiers",
                    "label": "op",
                    "offset": 0,
                    "slot": "0",
                    "type": "t_enum(StakingOperation)18160"
                },
                {
                    "astId": 18165,
                    "contract": "src/lib/LibGatewayActorStorage.sol:GatewayActorModifiers",
                    "label": "payload",
                    "offset": 0,
                    "slot": "1",
                    "type": "t_bytes_storage"
                },
                {
                    "astId": 18167,
                    "contract": "src/lib/LibGatewayActorStorage.sol:GatewayActorModifiers",
                    "label": "validator",
                    "offset": 0,
                    "slot": "2",
                    "type": "t_address"
                }
            ],
            "numberOfBytes": "96"
        },
        "t_struct(StakingChangeLog)18187_storage": {
            "encoding": "inplace",
            "label": "struct StakingChangeLog",
            "members": [
                {
                    "astId": 18177,
                    "contract": "src/lib/LibGatewayActorStorage.sol:GatewayActorModifiers",
                    "label": "nextConfigurationNumber",
                    "offset": 0,
                    "slot": "0",
                    "type": "t_uint64"
                },
                {
                    "astId": 18180,
                    "contract": "src/lib/LibGatewayActorStorage.sol:GatewayActorModifiers",
                    "label": "startConfigurationNumber",
                    "offset": 8,
                    "slot": "0",
                    "type": "t_uint64"
                },
                {
                    "astId": 18186,
                    "contract": "src/lib/LibGatewayActorStorage.sol:GatewayActorModifiers",
                    "label": "changes",
                    "offset": 0,
                    "slot": "1",
                    "type": "t_mapping(t_uint64,t_struct(StakingChange)18168_storage)"
                }
            ],
            "numberOfBytes": "64"
        },
        "t_struct(Subnet)18155_storage": {
            "encoding": "inplace",
            "label": "struct Subnet",
            "members": [
                {
                    "astId": 18143,
                    "contract": "src/lib/LibGatewayActorStorage.sol:GatewayActorModifiers",
                    "label": "stake",
                    "offset": 0,
                    "slot": "0",
                    "type": "t_uint256"
                },
                {
                    "astId": 18145,
                    "contract": "src/lib/LibGatewayActorStorage.sol:GatewayActorModifiers",
                    "label": "genesisEpoch",
                    "offset": 0,
                    "slot": "1",
                    "type": "t_uint256"
                },
                {
                    "astId": 18147,
                    "contract": "src/lib/LibGatewayActorStorage.sol:GatewayActorModifiers",
                    "label": "circSupply",
                    "offset": 0,
                    "slot": "2",
                    "type": "t_uint256"
                },
                {
                    "astId": 18149,
                    "contract": "src/lib/LibGatewayActorStorage.sol:GatewayActorModifiers",
                    "label": "topDownNonce",
                    "offset": 0,
                    "slot": "3",
                    "type": "t_uint64"
                },
                {
                    "astId": 18151,
                    "contract": "src/lib/LibGatewayActorStorage.sol:GatewayActorModifiers",
                    "label": "appliedBottomUpNonce",
                    "offset": 8,
                    "slot": "3",
                    "type": "t_uint64"
                },
                {
                    "astId": 18154,
                    "contract": "src/lib/LibGatewayActorStorage.sol:GatewayActorModifiers",
                    "label": "id",
                    "offset": 0,
                    "slot": "4",
                    "type": "t_struct(SubnetID)18141_storage"
                }
            ],
            "numberOfBytes": "192"
        },
        "t_struct(SubnetID)18141_storage": {
            "encoding": "inplace",
            "label": "struct SubnetID",
            "members": [
                {
                    "astId": 18136,
                    "contract": "src/lib/LibGatewayActorStorage.sol:GatewayActorModifiers",
                    "label": "root",
                    "offset": 0,
                    "slot": "0",
                    "type": "t_uint64"
                },
                {
                    "astId": 18140,
                    "contract": "src/lib/LibGatewayActorStorage.sol:GatewayActorModifiers",
                    "label": "route",
                    "offset": 0,
                    "slot": "1",
                    "type": "t_array(t_address)dyn_storage"
                }
            ],
            "numberOfBytes": "64"
        },
        "t_struct(UintSet)3971_storage": {
            "encoding": "inplace",
            "label": "struct EnumerableSet.UintSet",
            "members": [
                {
                    "astId": 3970,
                    "contract": "src/lib/LibGatewayActorStorage.sol:GatewayActorModifiers",
                    "label": "_inner",
                    "offset": 0,
                    "slot": "0",
                    "type": "t_struct(Set)3499_storage"
                }
            ],
            "numberOfBytes": "64"
        },
        "t_struct(Validator)18275_storage": {
            "encoding": "inplace",
            "label": "struct Validator",
            "members": [
                {
                    "astId": 18270,
                    "contract": "src/lib/LibGatewayActorStorage.sol:GatewayActorModifiers",
                    "label": "weight",
                    "offset": 0,
                    "slot": "0",
                    "type": "t_uint256"
                },
                {
                    "astId": 18272,
                    "contract": "src/lib/LibGatewayActorStorage.sol:GatewayActorModifiers",
                    "label": "addr",
                    "offset": 0,
                    "slot": "1",
                    "type": "t_address"
                },
                {
                    "astId": 18274,
                    "contract": "src/lib/LibGatewayActorStorage.sol:GatewayActorModifiers",
                    "label": "metadata",
                    "offset": 0,
                    "slot": "2",
                    "type": "t_bytes_storage"
                }
            ],
            "numberOfBytes": "96"
        },
        "t_struct(ValidatorInfo)18225_storage": {
            "encoding": "inplace",
            "label": "struct ValidatorInfo",
            "members": [
                {
                    "astId": 18217,
                    "contract": "src/lib/LibGatewayActorStorage.sol:GatewayActorModifiers",
                    "label": "federatedPower",
                    "offset": 0,
                    "slot": "0",
                    "type": "t_uint256"
                },
                {
                    "astId": 18219,
                    "contract": "src/lib/LibGatewayActorStorage.sol:GatewayActorModifiers",
                    "label": "confirmedCollateral",
                    "offset": 0,
                    "slot": "1",
                    "type": "t_uint256"
                },
                {
                    "astId": 18221,
                    "contract": "src/lib/LibGatewayActorStorage.sol:GatewayActorModifiers",
                    "label": "totalCollateral",
                    "offset": 0,
                    "slot": "2",
                    "type": "t_uint256"
                },
                {
                    "astId": 18224,
                    "contract": "src/lib/LibGatewayActorStorage.sol:GatewayActorModifiers",
                    "label": "metadata",
                    "offset": 0,
                    "slot": "3",
                    "type": "t_bytes_storage"
                }
            ],
            "numberOfBytes": "128"
        },
        "t_struct(ValidatorSet)18254_storage": {
            "encoding": "inplace",
            "label": "struct ValidatorSet",
            "members": [
                {
                    "astId": 18233,
                    "contract": "src/lib/LibGatewayActorStorage.sol:GatewayActorModifiers",
                    "label": "permissionMode",
                    "offset": 0,
                    "slot": "0",
                    "type": "t_enum(PermissionMode)18229"
                },
                {
                    "astId": 18236,
                    "contract": "src/lib/LibGatewayActorStorage.sol:GatewayActorModifiers",
                    "label": "activeLimit",
                    "offset": 1,
                    "slot": "0",
                    "type": "t_uint16"
                },
                {
                    "astId": 18239,
                    "contract": "src/lib/LibGatewayActorStorage.sol:GatewayActorModifiers",
                    "label": "totalConfirmedCollateral",
                    "offset": 0,
                    "slot": "1",
                    "type": "t_uint256"
                },
                {
                    "astId": 18245,
                    "contract": "src/lib/LibGatewayActorStorage.sol:GatewayActorModifiers",
                    "label": "validators",
                    "offset": 0,
                    "slot": "2",
                    "type": "t_mapping(t_address,t_struct(ValidatorInfo)18225_storage)"
                },
                {
                    "astId": 18249,
                    "contract": "src/lib/LibGatewayActorStorage.sol:GatewayActorModifiers",
                    "label": "activeValidators",
                    "offset": 0,
                    "slot": "3",
                    "type": "t_struct(MinPQ)17067_storage"
                },
                {
                    "astId": 18253,
                    "contract": "src/lib/LibGatewayActorStorage.sol:GatewayActorModifiers",
                    "label": "waitingValidators",
                    "offset": 0,
                    "slot": "6",
                    "type": "t_struct(MaxPQ)16449_storage"
                }
            ],
            "numberOfBytes": "288"
        },
        "t_uint16": {
            "encoding": "inplace",
            "label": "uint16",
            "numberOfBytes": "2"
        },
        "t_uint256": {
            "encoding": "inplace",
            "label": "uint256",
            "numberOfBytes": "32"
        },
        "t_uint64": {
            "encoding": "inplace",
            "label": "uint64",
            "numberOfBytes": "8"
        },
        "t_uint8": {
            "encoding": "inplace",
            "label": "uint8",
            "numberOfBytes": "1"
        }
    }
}
